nylas/__init__.py
nylas/_client_sdk_version.py
nylas/utils.py
nylas/client/__init__.py
nylas/client/client.py
nylas/client/errors.py
nylas/client/restful_model_collection.py
nylas/client/restful_models.py
tests/__init__.py
tests/conftest.py
tests/test_accounts.py
tests/test_client.py
tests/test_contacts.py
tests/test_drafts.py
tests/test_events.py
tests/test_files.py
tests/test_filter.py
tests/test_folders.py
tests/test_labels.py
tests/test_messages.py
tests/test_resources.py
tests/test_search.py
tests/test_send_error_handling.py
tests/test_threads.py
nylas-4.12.1.dist-info/LICENSE
nylas-4.12.1.dist-info/METADATA
nylas-4.12.1.dist-info/WHEEL
nylas-4.12.1.dist-info/top_level.txt
nylas-4.12.1.dist-info/RECORD
