Metadata-Version: 2.1
Name: nylas
Version: 4.12.1
Summary: Python bindings for Nylas, the next-generation email platform.
Home-page: https://github.com/nylas/nylas-python
Author: Nylas Team
Author-email: support@nylas.com
License: MIT
Keywords: inbox app appserver email nylas contacts calendar
Platform: UNKNOWN
Requires-Dist: requests[security] (>=2.4.2)
Requires-Dist: six (>=1.4.1)
Requires-Dist: bumpversion (>=0.5.0)
Requires-Dist: urlobject
Provides-Extra: test
Requires-Dist: pytest ; extra == 'test'
Requires-Dist: pytest-cov ; extra == 'test'
Requires-Dist: pytest-timeout ; extra == 'test'
Requires-Dist: responses (==0.10.5) ; extra == 'test'
Requires-Dist: twine ; extra == 'test'
